neotools/__init__.py
neotools/cli.py
neotools/commands.py
neotools/constants.py
neotools/device.py
neotools/file.py
neotools/main.py
neotools/message.py
neotools/text_file.py
neotools/util.py
neotools/applet/__init__.py
neotools/applet/applet.py
neotools/applet/constants.py
neotools/applet/manager.py
neotools/applet/settings.py
neotools/character_map/en-us.txt
neotools/character_map/ua-mac.txt
neotools-0.3.6.dist-info/LICENSE
neotools-0.3.6.dist-info/METADATA
neotools-0.3.6.dist-info/WHEEL
neotools-0.3.6.dist-info/entry_points.txt
neotools-0.3.6.dist-info/top_level.txt
neotools-0.3.6.dist-info/RECORD
