Metadata-Version: 2.1
Name: neotools
Version: 0.3.6
Summary: Command line tools for AlphaSmart NEO
Home-page: https://github.com/lykahb/neotools
Author: Borys Lykah
License: GNU GPL 3
Project-URL: Bug Tracker, https://github.com/lykahb/neotools/issues
Platform: unix
Platform: linux
Platform: osx
Platform: cygwin
Platform: win32
Classifier: Development Status :: 5 - Production/Stable
Classifier: Environment :: Console
Classifier: License :: OSI Approved :: GNU General Public License v3 (GPLv3)
Classifier: Programming Language :: Python
Classifier: Programming Language :: Python :: 3
Classifier: Programming Language :: Python :: 3 :: Only
Requires-Python: >=3.4
License-File: LICENSE
Requires-Dist: pyusb
Requires-Dist: click (>7)
Provides-Extra: testing
Requires-Dist: hypothesis (>5) ; extra == 'testing'
Requires-Dist: pytest ; extra == 'testing'
